Workbook

Sheet Read me
A1: ForgeX 2.0 Problem Bank
A4: Tags
A5: Tag | B5: Problems | C5: What it means | D5: Open to
A6: 🔵 Rare | B6: =COUNTIF(Problems!$C:$C,A6) -> 53 | C6: One clear user and one painful job. The fastest route to a working product and first paying users. | D6: Guided, or Structured with mentor sign-off
A7: 🟣 Epic | B7: =COUNTIF(Problems!$C:$C,A7) -> 98 | C7: A workflow product several types of users touch, with room to grow into a SaaS business. | D7: Guided and Structured
A8: 🟠 Legendary | B8: =COUNTIF(Problems!$C:$C,A8) -> 50 | C8: Several stakeholders or harder tech such as voice, vision or agents, in a large market. | D8: Structured and Autonomous
A9: 🔴 Mythic | B9: =COUNTIF(Problems!$C:$C,A9) -> 11 | C9: Frontier problems. Build one narrow slice brilliantly. | D9: Autonomous, with approval
A10: Total | B10: =SUM(B6:B9) -> 212 | C10: Autonomous students can also bring their own problem in the same format.
A12: Key dates
A13: Date | C13: What happens
A14: Oct 5, 10 am | C14: Bank released. Submit your top five by 8 pm.
A15: Oct 6, 9 am | C15: Allocations published. Swap window open until 9 am on Oct 7.
A16: Oct 7, 6 pm | C16: Gate 1: notes from five or more user conversations, today's workaround, why existing options fall short, the problem in your own words, your MVP bet with one metric, and how you'll reach your first 100 users.
A17: Oct 15, 6 pm | C17: Gate 2: a stranger completes your core flow on a live link without help.
A18: Oct 22 | C18: Pitch and defend: a five-minute live demo and ten minutes of questions.
A20: Rules for every problem
A21: Until Oct 7 you can narrow the user, change the geography or reframe the pain, as long as your user conversations support it. After that, changes need your POC's approval.
A22: Out of scope because Hackathon 1 covered them: itinerary planners, ranking job applicants, drones and self-driving vehicles, patient record systems and satellite crop monitoring.
A23: Payments run in test mode, WhatsApp runs on test numbers, and health, finance or children's data stays de-identified or synthetic.
A24: Facts and company examples were current on Oct 4, 2026. Check anything you plan to quote in your pitch.

Sheet Problems
A1: ID | B1: Title | C1: Tag | D1: Cluster | E1: Region | F1: Problem | G1: Who experiences it | H1: Why it matters | I1: Challenge | J1: North star metric | K1: Potential directions (examples only) | L1: Constraints | M1: Build expectation | N1: Tools to use
A2: P001 | B2: The credit that never comes back | C2: 🟣 Epic | D2: A. SMB, commerce and retail | E2: India | F2: Distributors of FMCG, pharma and hardware extend 15 to 60 days of credit to hundreds of retailers and track it in Tally, notebooks and the salesman's memory. Collection depends on who remembers to ask, and disputes over short supply or scheme credits hold payments up for weeks. | G2: Owners of distributorships with a few hundred retail accounts and a handful of salesmen. | H2: Distributors finance much of India's retail trade out of their own working capital, and overdue receivables cap how much stock they can carry. Lenders want to fund this layer but can't see a distributor's real ledger. | I2: Help distributors collect faster without straining their relationships with retailers. | J2: Days sales outstanding on a real distributor's ledger. | K2: a morning collection plan ranked by risk and relationship; settling disputes with retailers over WhatsApp before they block payment; clean ledger data turned into credit limits a lender would accept. | L2: Ledgers sit in desktop Tally, retailers dislike formal reminders, and owners share their books only once they trust you. | M2: Import one anonymised ledger, generate daily collection plans and run them with one distributor for a week. | N2: Data: Google Sheets, Python + pandas in Colab, Metabase or Supabase dashboards; WhatsApp: WhatsApp Cloud API (test number), Interakt or Gupshup, n8n
A3: P002 | B3: Stock that ages in the back room | C3: 🟣 Epic | D3: A. SMB, commerce and retail | E3: India | F3: Regional apparel and footwear chains end every season with stock they bought too much of, sitting in the wrong stores. Markdowns and transfers happen on gut feel, usually after the stock has lost most of its value. | G3: Owners and merchandisers at chains with 3 to 30 stores. | H3: Inventory planning software exists for India's large retailers, while regional chains still plan on spreadsheets. Money stuck in old stock can't buy what's selling. | I3: Help regional chains get stock to the store and price where it will sell before it goes stale. | J3: Full-price sell-through on a pilot set of items. | K3: transfers suggested from local sell-through; markdown timing; buyers for lots that won't sell at all. | L3: Sales data is messy across sizes and colours, and store managers resist giving stock away. | M3: Load a real sales export, generate weekly actions for 100+ items and review them with one retailer. | N3: Data: Google Sheets, Python + pandas in Colab, Metabase or Supabase dashboards
A4: P003 | B4: Quotes that arrive after the order is gone | C4: 🟣 Epic | D4: A. SMB, commerce and retail | E4: India | F4: Sheet-metal, machining, packaging and print shops get enquiries as drawings, PDFs and WhatsApp photos. Pricing a job takes an estimator hours or days, and a wrong guess on material or machine time wipes out the margin. | G4: Owners and estimators at manufacturers with 10 to 200 people. | H4: Buyers give the order to whoever quotes first with a believable number. Quoting software for job shops is a venture-backed category in the US (Paperless Parts), and Zetwerk grew large on the same pain from the buyer's side. | I4: Help small manufacturers quote faster and more accurately. | J4: Hours from enquiry to quote sent. | K4: drawings read into a bill of materials the estimator can edit; a costing model that learns from past jobs. | L4: Every shop costs differently, drawing quality varies, and past job data is thin. | M4: Quote ten real enquiries from one shop and compare with the estimator's numbers. | N4: Docs: Claude (reads PDFs and photos), Google Document AI or AWS Textract; Data: Google Sheets, Python + pandas in Colab, Metabase or Supabase dashboards
A5: P004 | B5: The supplier who raised prices without telling you | C5: 🔵 Rare | D5: A. SMB, commerce and retail | E5: Global | F5: Restaurants, clinics and small retailers buy from dozens of suppliers whose invoices change quietly: a higher rate, a smaller pack, an extra charge, a quantity that never arrived. Owners pay what the invoice says because nobody has time to check it against what was agreed. | G5: Owners and purchase managers at restaurants, retail chains and clinics. | H5: Spend-control software is a large category for big companies, and small businesses have none of it. AI can now read invoice photos well enough to compare every line with agreed rates. | I5: Help small businesses catch supplier overcharges before they pay. | J5: Rupees of overcharges caught per month at a pilot business. | K5: invoice photos checked against agreed rate cards; alerts on price creep by item; a monthly supplier scorecard. | L5: Handwritten invoices, rate agreements that live in people's heads, and supplier relationships. | M5: Check three months of real invoices for one business and quantify the overcharges. | N5: Docs: Claude (reads PDFs and photos), Google Document AI or AWS Textract; Data: Google Sheets, Python + pandas in Colab, Metabase or Supabase dashboards
A6: P005 | B6: Deductions modern trade takes from every payment | C6: 🟣 Epic | D6: A. SMB, commerce and retail | E6: India | F6: Emerging FMCG brands selling to DMart, Reliance Retail, More and regional supermarket chains rarely get paid the invoice amount. Retailers deduct for shortages, damages, expiry, promotions and listing fees, and brands can't match deductions to invoices or dispute them in time. | G6: Founders, finance and key-account teams at emerging FMCG and food brands, and their distributors. | H6: Deduction management is a funded software category for consumer brands in the US, where unresolved deductions cost a few percent of sales. Indian brands moving into modern trade face the same leak with nothing but spreadsheets. | I6: Help brands recover the deductions they shouldn't have taken. | J6: Value of invalid deductions recovered per month. | K6: matching remittances to invoices and proof of delivery; classifying each deduction as valid or disputable; dispute packs for the retailer. | L6: Remittance formats vary by retailer, proof of delivery is often on paper, and brands fear upsetting big buyers. | M6: Reconcile three months of one brand's modern-trade payments and file disputes for the invalid deductions. | N6: Docs: Claude (reads PDFs and photos), Google Document AI or AWS Textract; Data: Google Sheets, Python + pandas in Colab, Metabase or Supabase dashboards
A7: P006 | B7: Out of stock in a dark store you can't see | C7: 🟠 Legendary | D7: A. SMB, commerce and retail | E7: India | F7: Emerging brands on Blinkit, Zepto and Instamart sell through hundreds of dark stores but see little store-level availability. A product can be missing in key neighbourhoods for days before anyone notices. | G7: Founders and supply teams at young FMCG and D2C brands. | H7: Quick commerce has become one of the main growth channels for new consumer brands in Indian cities. An empty listing loses the sale on the spot and drops the product down search results. | I7: Help brands catch and fix availability gaps across dark stores. | J7: Share of target dark stores where the hero product is in stock, tracked daily. | K7: availability monitoring by pin code; demand forecasts by micro-market that feed purchase orders; playbooks for distributors and platform managers. | L7: Platform data access is limited, and monitoring must follow platform terms. | M7: Map availability across 20+ locations for one real brand for a week and record the actions it led to. | N7: Data: Google Sheets, Python + pandas in Colab, Metabase or Supabase dashboards; Agents: Claude tool use and MCP, Playwright or Browserbase, Firecrawl
A8: P007 | B8: Cash that leaks at the billing counter | C8: 🟣 Epic | D8: A. SMB, commerce and retail | E8: India | F8: Regional retail chains, restaurants and pharmacies lose money at the counter through voided bills, unexplained discounts, fake returns and cash that never reaches the bank. Owners see only the daily total and catch problems months later, if ever. | G8: Owners and operations heads at chains with 3 to 50 outlets. | H8: Large retailers run loss-prevention analytics on every transaction, and small chains run on trust. Leakage of one or two percent of sales can equal a chain's whole profit. | I8: Help small chains spot and stop leakage at the billing counter. | J8: Suspicious transactions flagged and confirmed per outlet per week. | K8: exception reports from POS exports; patterns by cashier, shift and outlet; daily cash reconciliation against bank deposits. | L8: POS systems export differently, staff must be treated fairly, and owners need proof before acting. | M8: Analyse three months of POS data from one chain and review the flagged cases with the owner. | N8: Data: Google Sheets, Python + pandas in Colab, Metabase or Supabase dashboards
A9: P008 | B9: Orders that arrive as voice notes and notebook photos | C9: 🟠 Legendary | D9: A. SMB, commerce and retail | E9: India | F9: Wholesalers get WhatsApp orders as voice notes in mixed languages, photos of handwritten lists and forwarded messages. Billing staff type everything in again, with mistakes. | G9: Wholesalers and distributors of groceries, hardware, pharma and stationery, and their billing staff. | H9: WhatsApp is the ordering system for much of India's B2B trade, and AI can now read voice notes and handwriting well enough to structure it. Wrong deliveries cause disputes, and peak-hour backlogs cap how many customers a trader can serve. | I9: Turn messy inbound orders into confirmed, correct orders with little manual work. | J9: Share of orders that reach the billing system with no human retyping. | K9: a WhatsApp intake that reads line items and confirms back; catalogue matching that understands local product names. | L9: Product names are colloquial, so catalogue mapping is the hard part, and WhatsApp API setup takes time. | M9: Process 100 real orders from one trader and run the confirmation loop live. | N9: WhatsApp: WhatsApp Cloud API (test number), Interakt or Gupshup, n8n; Voice: Sarvam AI, Deepgram or Whisper, ElevenLabs, Vapi or Retell, Exotel or Twilio
A10: P009 | B10: A quarter of every delivery order goes to the app | C10: 🔵 Rare | D10: A. SMB, commerce and retail | E10: Middle East | F10: Restaurants in Dubai and Abu Dhabi depend on Talabat, Deliveroo and Careem for delivery and hand over a large commission on every order. Regulars who would happily order direct have no easy way to do it, and the restaurant never learns who they are. | G10: Owners of independent restaurants and small chains in the UAE. Indian restaurants face the same split with Swiggy and Zomato. | H10: Talabat listed on the Dubai Financial Market in December 2024, which shows how much value sits with the platform. Restaurants keep the food cost and give away both margin and the customer relationship. | I10: Help restaurants move repeat customers to direct ordering without losing reach. | J10: Share of repeat orders placed direct at a pilot restaurant. | K10: a direct-ordering link with WhatsApp confirmation and loyalty pricing; bringing past customers back through packaging and receipts. | L10: Platform contracts may limit pricing, restaurants need their own riders or a delivery partner, and customers like having one app. | M10: Set up direct ordering for one restaurant in the UAE or Bengaluru and track repeat orders for two weeks. | N10: WhatsApp: WhatsApp Cloud API (test number), Interakt or Gupshup, n8n; Payments: Razorpay or Stripe in test mode, Setu sandbox
A11: P010 | B11: A year's rent in four cheques | C11: 🔵 Rare | D11: A. SMB, commerce and retail | E11: Middle East | F11: Tenants in the UAE usually pay a year's rent upfront or in one to four post-dated cheques. New arrivals and young professionals struggle to find that much cash, and landlords prefer fewer cheques because bounced ones are a headache. | G11: Tenants in Dubai and Abu Dhabi, landlords and property managers. | H11: Several UAE startups have raised funding to let tenants pay monthly while landlords still get the year upfront. The model works when tenant risk is priced well, and that risk data is the hard part. | I11: Make renting in the UAE affordable month to month without adding risk for landlords. | J11: Share of applicants a landlord accepts on monthly terms with no rise in missed payments. | K11: tenant risk assessment from salary and employer data; financing the gap between monthly payments and upfront cheques; guarantees for landlords. | L11: Central bank and real estate rules, Ejari registration, and access to salary data. | M11: Model the economics on realistic data and test the offer with ten tenants and three property managers online. | N11: Data: Google Sheets, Python + pandas in Colab, Metabase or Supabase dashboards; Payments: Razorpay or Stripe in test mode, Setu sandbox
A12: P011 | B12: Two hundred order-taking calls a day | C12: 🟠 Legendary | D12: A. SMB, commerce and retail | E12: India | F12: Distributors of FMCG, pharma and building materials employ tele-callers who phone retailers every day to take orders. Calls run long, retailers forget items, and orders get written down wrong in a mix of Hindi, Kannada and English. | G12: Distributor owners and their tele-calling teams, and the retailers who order from them. | H12: Phone ordering still carries a large share of India's B2B trade, and voice AI in Indian languages became good and cheap enough for real calls in 2025. A voice agent that takes orders reliably could serve distributors across the country. | I12: Help distributors take accurate phone orders at scale. | J12: Share of order calls completed with a correct order and no human help. | K12: an outbound voice agent that calls retailers, suggests reorders and confirms the order; handoff to a human on hard calls; orders pushed into the billing system. | L12: Speech quality across languages and noisy shops, retailers' patience, and product names that vary by area. | M12: Run the agent on 50 real or role-played order calls using one distributor's catalogue. | N12: Voice: Sarvam AI, Deepgram or Whisper, ElevenLabs, Vapi or Retell, Exotel or Twilio; Data: Google Sheets, Python + pandas in Colab, Metabase or Supabase dashboards
... A213: P212 | B213: Ordering by voice when you can't read the screen | C213: 🟠 Legendary | D213: J. Problems created by AI, AI agents and accessibility | E213: India | F213: Many Indians with low literacy struggle with text-heavy apps for booking gas cylinders, ordering groceries or paying bills. They ask others for help or skip digital services entirely. | G213: Low-literacy users and the businesses that serve them. | H213: A very large number of people could use digital services if the interface suited them. | I213: Let low-literacy users complete transactions by voice in their own language. | J213: Share of voice orders completed without an error. | K213: voice-first ordering over WhatsApp; spoken confirmation before payment; support for local dialects. | L213: Speech recognition for dialects, and mistakes that involve money. | M213: Test with 15 users ordering from one business. | N213: Voice: Sarvam AI, Deepgram or Whisper, ElevenLabs, Vapi or Retell, Exotel or Twilio; WhatsApp: WhatsApp Cloud API (test number), Interakt or Gupshup, n8n

Sheet Tech stack
A1: Tech stack and tools
A2: Every problem can be built with the core stack plus one or two tool kits. Most tools have a free tier or student credits. Check with your POC before paying for anything.
A4: Core stack for everyone
A5: Need | B5: Use | C5: What it does
A6: Build the app | B6: Claude Code, Lovable, Bolt or Replit | C6: Writes and edits working code from plain-English instructions
A7: Database and login | B7: Supabase | C7: Hosted database, user accounts and file storage
A8: Hosting | B8: Vercel or Netlify | C8: Puts your app on a live link in one click, which Gate 2 needs
A9: AI model | B9: Claude API | C9: Reasoning, writing, reading documents and images, and agents
A10: Automations | B10: n8n, Make or Zapier | C10: Connects apps and runs workflows without integration code
A11: User research | B11: Tally or Google Forms, Google Meet, Otter | C11: Surveys, interviews and notes for Gate 1
A12: Analytics | B12: PostHog | C12: Tracks your north star metric from the first user
A14: Tool kits
A15: Kit | B15: Use it when | C15: Tools
A16: WhatsApp | B16: Your users live on WhatsApp | C16: WhatsApp Cloud API (test number), Interakt or Gupshup, n8n
A17: Voice | B17: Calls, voice notes or Indian languages | C17: Sarvam AI, Deepgram or Whisper, ElevenLabs, Vapi or Retell, Exotel or Twilio
A18: Docs | B18: Invoices, bills, contracts, forms or filings | C18: Claude (reads PDFs and photos), Google Document AI or AWS Textract
A19: Vision | B19: Photos of products, parts, sites or people | C19: Claude vision, Roboflow
A20: Data | B20: Sales exports, ledgers, prices or forecasts | C20: Google Sheets, Python + pandas in Colab, Metabase or Supabase dashboards
A21: Agents | B21: Tasks that span websites, inboxes or tools | C21: Claude tool use and MCP, Playwright or Browserbase, Firecrawl
A22: Maps | B22: Routes, addresses, sites or travel | C22: Google Maps Platform, Mapbox, Ola Maps, OpenStreetMap
A23: Payments | B23: Billing, credit or money movement | C23: Razorpay or Stripe in test mode, Setu sandbox
A24: Mobile | B24: Low-end phones or patchy networks | C24: Progressive web app, Expo (React Native), MSG91 or Twilio SMS
A26: Rules for tools
A27: Keep API keys in your platform's environment settings. Never paste them into code, chat or a shared doc.
A28: Payments run in test mode and WhatsApp runs on test numbers.
A29: Scrape only public pages and respect each site's terms.
A30: Your build log should say which tools you used and why.

Sheet Summary
A1: Problems by cluster and tag
A3: Cluster | B3: 🔵 Rare | C3: 🟣 Epic | D3: 🟠 Legendary | E3: 🔴 Mythic | F3: Total
A4: A. SMB, commerce and retail | B4: =COUNTIFS(Problems!$D:$D,$A4,Problems!$C:$C,B$3) -> 7 | C4: =COUNTIFS(Problems!$D:$D,$A4,Problems!$C:$C,C$3) -> 7 | D4: =COUNTIFS(Problems!$D:$D,$A4,Problems!$C:$C,D$3) -> 7 | E4: =COUNTIFS(Problems!$D:$D,$A4,Problems!$C:$C,E$3) -> 0 | F4: =SUM(B4:E4) -> 21
A5: B. Healthcare and wellbeing | B5: =COUNTIFS(Problems!$D:$D,$A5,Problems!$C:$C,B$3) -> 5 | C5: =COUNTIFS(Problems!$D:$D,$A5,Problems!$C:$C,C$3) -> 9 | D5: =COUNTIFS(Problems!$D:$D,$A5,Problems!$C:$C,D$3) -> 5 | E5: =COUNTIFS(Problems!$D:$D,$A5,Problems!$C:$C,E$3) -> 2 | F5: =SUM(B5:E5) -> 21
A6: C. Education, skills and careers | B6: =COUNTIFS(Problems!$D:$D,$A6,Problems!$C:$C,B$3) -> 5 | C6: =COUNTIFS(Problems!$D:$D,$A6,Problems!$C:$C,C$3) -> 10 | D6: =COUNTIFS(Problems!$D:$D,$A6,Problems!$C:$C,D$3) -> 5 | E6: =COUNTIFS(Problems!$D:$D,$A6,Problems!$C:$C,E$3) -> 1 | F6: =SUM(B6:E6) -> 21
A7: D. Money: fintech, insurance and cross-border | B7: =COUNTIFS(Problems!$D:$D,$A7,Problems!$C:$C,B$3) -> 4 | C7: =COUNTIFS(Problems!$D:$D,$A7,Problems!$C:$C,C$3) -> 12 | D7: =COUNTIFS(Problems!$D:$D,$A7,Problems!$C:$C,D$3) -> 4 | E7: =COUNTIFS(Problems!$D:$D,$A7,Problems!$C:$C,E$3) -> 1 | F7: =SUM(B7:E7) -> 21
A8: E. Work: workforce, legal and knowledge work | B8: =COUNTIFS(Problems!$D:$D,$A8,Problems!$C:$C,B$3) -> 8 | C8: =COUNTIFS(Problems!$D:$D,$A8,Problems!$C:$C,C$3) -> 8 | D8: =COUNTIFS(Problems!$D:$D,$A8,Problems!$C:$C,D$3) -> 5 | E8: =COUNTIFS(Problems!$D:$D,$A8,Problems!$C:$C,E$3) -> 0 | F8: =SUM(B8:E8) -> 21
A9: F. Climate, energy, food and agriculture | B9: =COUNTIFS(Problems!$D:$D,$A9,Problems!$C:$C,B$3) -> 4 | C9: =COUNTIFS(Problems!$D:$D,$A9,Problems!$C:$C,C$3) -> 12 | D9: =COUNTIFS(Problems!$D:$D,$A9,Problems!$C:$C,D$3) -> 5 | E9: =COUNTIFS(Problems!$D:$D,$A9,Problems!$C:$C,E$3) -> 1 | F9: =SUM(B9:E9) -> 22
A10: G. Cities, mobility, logistics and real estate | B10: =COUNTIFS(Problems!$D:$D,$A10,Problems!$C:$C,B$3) -> 4 | C10: =COUNTIFS(Problems!$D:$D,$A10,Problems!$C:$C,C$3) -> 11 | D10: =COUNTIFS(Problems!$D:$D,$A10,Problems!$C:$C,D$3) -> 5 | E10: =COUNTIFS(Problems!$D:$D,$A10,Problems!$C:$C,E$3) -> 2 | F10: =SUM(B10:E10) -> 22
A11: H. Consumer, creators, travel and hospitality | B11: =COUNTIFS(Problems!$D:$D,$A11,Problems!$C:$C,B$3) -> 9 | C11: =COUNTIFS(Problems!$D:$D,$A11,Problems!$C:$C,C$3) -> 10 | D11: =COUNTIFS(Problems!$D:$D,$A11,Problems!$C:$C,D$3) -> 2 | E11: =COUNTIFS(Problems!$D:$D,$A11,Problems!$C:$C,E$3) -> 0 | F11: =SUM(B11:E11) -> 21
A12: I. Industry, supply chain, security and dev tools | B12: =COUNTIFS(Problems!$D:$D,$A12,Problems!$C:$C,B$3) -> 4 | C12: =COUNTIFS(Problems!$D:$D,$A12,Problems!$C:$C,C$3) -> 11 | D12: =COUNTIFS(Problems!$D:$D,$A12,Problems!$C:$C,D$3) -> 6 | E12: =COUNTIFS(Problems!$D:$D,$A12,Problems!$C:$C,E$3) -> 0 | F12: =SUM(B12:E12) -> 21
A13: J. Problems created by AI, AI agents and accessibility | B13: =COUNTIFS(Problems!$D:$D,$A13,Problems!$C:$C,B$3) -> 3 | C13: =COUNTIFS(Problems!$D:$D,$A13,Problems!$C:$C,C$3) -> 8 | D13: =COUNTIFS(Problems!$D:$D,$A13,Problems!$C:$C,D$3) -> 6 | E13: =COUNTIFS(Problems!$D:$D,$A13,Problems!$C:$C,E$3) -> 4 | F13: =SUM(B13:E13) -> 21
A14: Total | B14: =SUM(B4:B13) -> 53 | C14: =SUM(C4:C13) -> 98 | D14: =SUM(D4:D13) -> 50 | E14: =SUM(E4:E13) -> 11 | F14: =SUM(F4:F13) -> 212
